src/csr.v
// csr.v - APB control/status registers for QSPI controller
// Implements zero wait-state APB3/4 slave. Register map stops at 0x050.
// CTRL[8] is CMD_TRIGGER (write-one-to-start) which generates a one-cycle
// cmd_start_o pulse and is cleared by cmd_trigger_clr_i from the command
// engine. Trigger is ignored when CTRL.enable=0, XIP_EN=1 or busy_i=1.
// CMD_TRIGGER when busy_i generates PSLVERR. XIP_EN writes while busy or
// DMA enabled are ignored. CMD and XIP modes are mutually exclusive.
// All registers use synchronous active-low reset.

module csr #(
  parameter integer APB_ADDR_WIDTH = 12,
  parameter integer APB_WINDOW_LSB = 12,  // 4KB window
  parameter integer HAS_PSTRB      = 0,   // 0: ignore pstrb
  parameter integer HAS_WP         = 0    // 1: CTRL[10] writable
)(
  // APB interface
  input  wire                     pclk,
  input  wire                     presetn,
  input  wire                     psel,
  input  wire                     penable,
  input  wire                     pwrite,
  input  wire [APB_ADDR_WIDTH-1:0] paddr,
  input  wire [31:0]              pwdata,
  input  wire [3:0]               pstrb,
  output reg  [31:0]              prdata,
  output wire                     pready,
  output reg                      pslverr,

  // CTRL outputs
  output wire enable_o,
  output wire xip_en_o,
  output wire quad_en_o,
  output wire cpol_o,
  output wire cpha_o,
  output wire lsb_first_o,
  output wire cmd_start_o,
  output wire dma_en_o,
  output wire mode_en_o,
  output wire hold_en_o,
  output wire wp_en_o,

  // clear from command engine
  input  wire cmd_trigger_clr_i,

  // Clock & CS
  output wire [2:0] clk_div_o,
  output wire       cs_auto_o,
  output wire [1:0] cs_level_o,
  output wire [1:0] cs_delay_o,

  // XIP configuration
  output wire [1:0] xip_addr_bytes_o,
  output wire [1:0] xip_data_lanes_o,
  output wire [3:0] xip_dummy_cycles_o,
  output wire       xip_cont_read_o,
  output wire       xip_mode_en_o,
  output wire       xip_write_en_o,
  output wire [7:0] xip_read_op_o,
  output wire [7:0] xip_mode_bits_o,
  output wire [7:0] xip_write_op_o,

  // Command configuration
  output wire [1:0] cmd_lanes_o,
  output wire [1:0] addr_lanes_o,
  output wire [1:0] data_lanes_o,
  output wire [1:0] addr_bytes_o,
  output wire       mode_en_cfg_o,
  output wire [3:0] dummy_cycles_o,
  output wire       is_write_o,
  output wire [7:0] opcode_o,
  output wire [7:0] mode_bits_o,
  output wire [31:0] cmd_addr_o,
  output wire [31:0] cmd_len_o,
  output wire [7:0] extra_dummy_o,

  // DMA configuration
  output wire [3:0]  burst_size_o,
  output wire        dma_dir_o,
  output wire        incr_addr_o,
  output wire [31:0] dma_addr_o,
  output wire [31:0] dma_len_o,

  // FIFO windows
  output wire [31:0] fifo_tx_data_o,
  output wire        fifo_tx_we_o,
  input  wire [31:0] fifo_rx_data_i,
  output wire        fifo_rx_re_o,

  // Interrupts
  output wire [4:0] int_en_o,
  input  wire cmd_done_set_i,
  input  wire dma_done_set_i,
  input  wire err_set_i,
  input  wire fifo_tx_empty_set_i,
  input  wire fifo_rx_full_set_i,

  // Status inputs
  input  wire busy_i,
  input  wire xip_active_i,
  input  wire cmd_done_i,
  input  wire dma_done_i,
  input  wire [3:0] tx_level_i,
  input  wire [3:0] rx_level_i,
  input  wire tx_empty_i,
  input  wire rx_full_i,
  input  wire timeout_i,
  input  wire overrun_i,
  input  wire underrun_i,
  input  wire axi_err_i,
  output wire irq
);

  // ---------------------------------------------------------
  // APB basic signals
  wire setup_phase  = psel & ~penable;
  wire access_phase = psel & penable;
  wire write_phase  = access_phase & pwrite;
  wire read_phase   = access_phase & ~pwrite;
  assign pready = 1'b1;                       // zero wait-state
  wire [3:0] pstrb_eff = (HAS_PSTRB!=0) ? pstrb : 4'b1111;

  // address window (map stops at 0x050)
  localparam integer WIN = APB_WINDOW_LSB;
  wire [WIN-1:0] a = paddr[WIN-1:0];

  localparam [WIN-1:0] ID_ADDR        = 'h000;
  localparam [WIN-1:0] CTRL_ADDR      = 'h004;
  localparam [WIN-1:0] STATUS_ADDR    = 'h008;
  localparam [WIN-1:0] INT_EN_ADDR    = 'h00C;
  localparam [WIN-1:0] INT_STAT_ADDR  = 'h010; // W1C
  localparam [WIN-1:0] CLK_DIV_ADDR   = 'h014;
  localparam [WIN-1:0] CS_CTRL_ADDR   = 'h018;
  localparam [WIN-1:0] XIP_CFG_ADDR   = 'h01C;
  localparam [WIN-1:0] XIP_CMD_ADDR   = 'h020;
  localparam [WIN-1:0] CMD_CFG_ADDR   = 'h024;
  localparam [WIN-1:0] CMD_OP_ADDR    = 'h028;
  localparam [WIN-1:0] CMD_ADDR_ADDR  = 'h02C;
  localparam [WIN-1:0] CMD_LEN_ADDR   = 'h030;
  localparam [WIN-1:0] CMD_DUMMY_ADDR = 'h034;
  localparam [WIN-1:0] DMA_CFG_ADDR   = 'h038;
  localparam [WIN-1:0] DMA_DST_ADDR   = 'h03C;
  localparam [WIN-1:0] DMA_LEN_ADDR   = 'h040;
  localparam [WIN-1:0] FIFO_TX_ADDR   = 'h044;
  localparam [WIN-1:0] FIFO_RX_ADDR   = 'h048;
  localparam [WIN-1:0] FIFO_STAT_ADDR = 'h04C;
  localparam [WIN-1:0] ERR_STAT_ADDR  = 'h050;

  // ---------------------------------------------------------
  // Registers
  reg [31:0] ctrl_reg, int_en_reg, int_stat_reg;
  reg [31:0] clk_div_reg, cs_ctrl_reg;
  reg [31:0] xip_cfg_reg, xip_cmd_reg;
  reg [31:0] cmd_cfg_reg, cmd_op_reg, cmd_addr_reg, cmd_len_reg, cmd_dummy_reg;
  reg [31:0] dma_cfg_reg, dma_addr_reg, dma_len_reg;
  reg [31:0] err_stat_reg;

  // fixed values
  localparam [31:0] ID_VALUE = 32'h1A00_1081;

  // status latches for cmd/dma done
  reg cmd_done_latched, dma_done_latched;

  // ---------------------------------------------------------
  // Address decode
  reg valid_addr, ro_addr;
  always @(*) begin
    valid_addr = 1'b0;
    ro_addr    = 1'b0;
    case (a)
      ID_ADDR        : begin valid_addr=1'b1; ro_addr=1'b1; end
      CTRL_ADDR      : begin valid_addr=1'b1; end
      STATUS_ADDR    : begin valid_addr=1'b1; ro_addr=1'b1; end
      INT_EN_ADDR    : begin valid_addr=1'b1; end
      INT_STAT_ADDR  : begin valid_addr=1'b1; end
      CLK_DIV_ADDR   : begin valid_addr=1'b1; end
      CS_CTRL_ADDR   : begin valid_addr=1'b1; end
      XIP_CFG_ADDR   : begin valid_addr=1'b1; end
      XIP_CMD_ADDR   : begin valid_addr=1'b1; end
      CMD_CFG_ADDR   : begin valid_addr=1'b1; end
      CMD_OP_ADDR    : begin valid_addr=1'b1; end
      CMD_ADDR_ADDR  : begin valid_addr=1'b1; end
      CMD_LEN_ADDR   : begin valid_addr=1'b1; end
      CMD_DUMMY_ADDR : begin valid_addr=1'b1; end
      DMA_CFG_ADDR   : begin valid_addr=1'b1; end
      DMA_DST_ADDR   : begin valid_addr=1'b1; end
      DMA_LEN_ADDR   : begin valid_addr=1'b1; end
      FIFO_TX_ADDR   : begin valid_addr=1'b1; end
      FIFO_RX_ADDR   : begin valid_addr=1'b1; ro_addr=1'b1; end
      FIFO_STAT_ADDR : begin valid_addr=1'b1; ro_addr=1'b1; end
      ERR_STAT_ADDR  : begin valid_addr=1'b1; end
      default        : begin valid_addr=1'b0; ro_addr=1'b0; end
    endcase
  end

  // ---------------------------------------------------------
  // PSLVERR generation
  always @(*) begin
    pslverr = 1'b0;
    if (write_phase) begin
      if (!valid_addr || ro_addr)
        pslverr = 1'b1;
      else if ((a==CTRL_ADDR) && pstrb_eff[1] && pwdata[8] && busy_i)
        pslverr = 1'b1; // busy lockout
    end
  end

  // global write enable
  wire wr_ok = write_phase & valid_addr & ~ro_addr;

  // FIFO side effects
  assign fifo_tx_we_o  = wr_ok & (a==FIFO_TX_ADDR);
  assign fifo_tx_data_o = pwdata;
  assign fifo_rx_re_o  = read_phase & valid_addr & (a==FIFO_RX_ADDR);

  // ---------------------------------------------------------
  // Write masks
  wire [31:0] CTRL_WMASK = (HAS_WP!=0) ? 32'h0000_06FF : 32'h0000_02FF; // bit8 excluded
  wire [31:0] CLKDIV_WMASK = 32'h0000_000F;
  wire [31:0] CSCTRL_WMASK = 32'h0000_001F;
  wire [31:0] XIPCFG_WMASK = 32'h0000_3FFF;
  wire [31:0] XIPCMD_WMASK = 32'h00FF_FFFF;
  wire [31:0] CMDCFG_WMASK = 32'h0000_1FFF;
  wire [31:0] CMDOP_WMASK  = 32'h0000_FFFF;
  wire [31:0] CMDDMY_WMASK = 32'h0000_00FF;
  wire [31:0] DMACFG_WMASK = 32'h0000_003F;

  // helper for byte-masked writes
  function [31:0] apply_strb;
    input [31:0] cur;
    input [31:0] data;
    begin
      apply_strb = {
        pstrb_eff[3] ? data[31:24] : cur[31:24],
        pstrb_eff[2] ? data[23:16] : cur[23:16],
        pstrb_eff[1] ? data[15:8]  : cur[15:8],
        pstrb_eff[0] ? data[7:0]   : cur[7:0]
      };
    end
  endfunction

  // ---------------------------------------------------------
  // CMD_TRIGGER handling (W1S)
  wire cmd_trig_wr = wr_ok & (a==CTRL_ADDR) & pstrb_eff[1] & pwdata[8];
  wire cmd_trig_ok = cmd_trig_wr & ctrl_reg[0] & ~ctrl_reg[1] & ~busy_i;
  reg  cmd_trig_q;
  always @(posedge pclk or negedge presetn) begin
    if (!presetn) cmd_trig_q <= 1'b0;
    else if (cmd_trigger_clr_i) cmd_trig_q <= 1'b0;
    else if (cmd_trig_ok) cmd_trig_q <= 1'b1;
  end
  assign cmd_start_o = cmd_trig_q; // one-cycle pulse when CE acks

  // ---------------------------------------------------------
  // Register writes
  always @(posedge pclk or negedge presetn) begin
    if (!presetn) begin
      ctrl_reg      <= 32'h0;
      int_en_reg    <= 32'h0;
      int_stat_reg  <= 32'h0;
      clk_div_reg   <= 32'h0;
      cs_ctrl_reg   <= 32'h0000_0001; // default CS auto=1
      xip_cfg_reg   <= 32'h0;
      xip_cmd_reg   <= 32'h0;
      cmd_cfg_reg   <= 32'h0;
      cmd_op_reg    <= 32'h0;
      cmd_addr_reg  <= 32'h0;
      cmd_len_reg   <= 32'h0;
      cmd_dummy_reg <= 32'h0;
      dma_cfg_reg   <= 32'h0;
      dma_addr_reg  <= 32'h0;
      dma_len_reg   <= 32'h0;
      err_stat_reg  <= 32'h0;
      cmd_done_latched <= 1'b0;
      dma_done_latched <= 1'b0;
    end else begin
      // CTRL write with masks
      if (wr_ok && (a==CTRL_ADDR)) begin
        reg [31:0] next_ctrl;
        next_ctrl = apply_strb(ctrl_reg, pwdata);
        next_ctrl = (next_ctrl & CTRL_WMASK) | (ctrl_reg & ~CTRL_WMASK);
        // ignore XIP_EN if busy or DMA
        if (busy_i || next_ctrl[6] || ctrl_reg[6])
          next_ctrl[1] = ctrl_reg[1];
        ctrl_reg <= next_ctrl;
      end

      // INT_EN (bits [4:0] in byte0)
      if (wr_ok && (a==INT_EN_ADDR)) begin
        int_en_reg[4:0] <= pstrb_eff[0] ? pwdata[4:0] : int_en_reg[4:0];
      end

      if (wr_ok && (a==CLK_DIV_ADDR))
        clk_div_reg <= apply_strb(clk_div_reg, pwdata) & CLKDIV_WMASK;
      if (wr_ok && (a==CS_CTRL_ADDR))
        cs_ctrl_reg <= apply_strb(cs_ctrl_reg, pwdata) & CSCTRL_WMASK;
      if (wr_ok && (a==XIP_CFG_ADDR))
        xip_cfg_reg <= apply_strb(xip_cfg_reg, pwdata) & XIPCFG_WMASK;
      if (wr_ok && (a==XIP_CMD_ADDR))
        xip_cmd_reg <= apply_strb(xip_cmd_reg, pwdata) & XIPCMD_WMASK;
      if (wr_ok && (a==CMD_CFG_ADDR))
        cmd_cfg_reg <= apply_strb(cmd_cfg_reg, pwdata) & CMDCFG_WMASK;
      if (wr_ok && (a==CMD_OP_ADDR))
        cmd_op_reg <= apply_strb(cmd_op_reg, pwdata) & CMDOP_WMASK;
      if (wr_ok && (a==CMD_ADDR_ADDR))
        cmd_addr_reg <= apply_strb(cmd_addr_reg, pwdata);
      if (wr_ok && (a==CMD_LEN_ADDR))
        cmd_len_reg <= apply_strb(cmd_len_reg, pwdata);
      if (wr_ok && (a==CMD_DUMMY_ADDR))
        cmd_dummy_reg <= apply_strb(cmd_dummy_reg, pwdata) & CMDDMY_WMASK;
      if (wr_ok && (a==DMA_CFG_ADDR))
        dma_cfg_reg <= apply_strb(dma_cfg_reg, pwdata) & DMACFG_WMASK;
      if (wr_ok && (a==DMA_DST_ADDR))
        dma_addr_reg <= apply_strb(dma_addr_reg, pwdata);
      if (wr_ok && (a==DMA_LEN_ADDR))
        dma_len_reg <= apply_strb(dma_len_reg, pwdata);

      // INT_STAT W1C
      if (wr_ok && (a==INT_STAT_ADDR))
        int_stat_reg <= int_stat_reg & ~pwdata;

      // ERR_STAT W1C
      if (wr_ok && (a==ERR_STAT_ADDR))
        err_stat_reg <= err_stat_reg & ~pwdata;

      // latch status/interrupt sources
      if (cmd_done_set_i) begin
        int_stat_reg[0] <= 1'b1;
        cmd_done_latched <= 1'b1;
      end
      if (dma_done_set_i) begin
        int_stat_reg[1] <= 1'b1;
        dma_done_latched <= 1'b1;
      end
      if (err_set_i) int_stat_reg[2] <= 1'b1;
      if (fifo_tx_empty_set_i) int_stat_reg[3] <= 1'b1;
      if (fifo_rx_full_set_i) int_stat_reg[4] <= 1'b1;

      // error status bits
      if (timeout_i)  err_stat_reg[0] <= 1'b1;
      if (overrun_i)  err_stat_reg[1] <= 1'b1;
      if (underrun_i) err_stat_reg[2] <= 1'b1;
      if (axi_err_i)  err_stat_reg[3] <= 1'b1;

      // status W1C clears
      if (wr_ok && (a==STATUS_ADDR) && pstrb_eff[0]) begin
        if (pwdata[0]) cmd_done_latched <= 1'b0;
        if (pwdata[1]) dma_done_latched <= 1'b0;
      end
    end
  end

  // ---------------------------------------------------------
  // Read mux
  always @(*) begin
    prdata = 32'h0;
    if (read_phase && valid_addr) begin
      case (a)
        ID_ADDR        : prdata = ID_VALUE;
        CTRL_ADDR      : prdata = ctrl_reg;
        STATUS_ADDR    : prdata = {20'd0, rx_level_i, tx_level_i, busy_i, xip_active_i, cmd_done_latched, dma_done_latched};
        INT_EN_ADDR    : prdata = int_en_reg;
        INT_STAT_ADDR  : prdata = int_stat_reg;
        CLK_DIV_ADDR   : prdata = clk_div_reg;
        CS_CTRL_ADDR   : prdata = cs_ctrl_reg;
        XIP_CFG_ADDR   : prdata = xip_cfg_reg;
        XIP_CMD_ADDR   : prdata = xip_cmd_reg;
        CMD_CFG_ADDR   : prdata = cmd_cfg_reg;
        CMD_OP_ADDR    : prdata = cmd_op_reg;
        CMD_ADDR_ADDR  : prdata = cmd_addr_reg;
        CMD_LEN_ADDR   : prdata = cmd_len_reg;
        CMD_DUMMY_ADDR : prdata = cmd_dummy_reg;
        DMA_CFG_ADDR   : prdata = dma_cfg_reg;
        DMA_DST_ADDR   : prdata = dma_addr_reg;
        DMA_LEN_ADDR   : prdata = dma_len_reg;
        FIFO_RX_ADDR   : prdata = fifo_rx_data_i;
        FIFO_STAT_ADDR : prdata = {22'd0, rx_full_i, tx_empty_i, rx_level_i, tx_level_i};
        ERR_STAT_ADDR  : prdata = err_stat_reg;
        default        : prdata = 32'h0;
      endcase
    end
  end

  // ---------------------------------------------------------
  // Field mapping
  assign enable_o      = ctrl_reg[0];
  assign xip_en_o      = ctrl_reg[1];
  assign quad_en_o     = ctrl_reg[2]; // set only after flash QE set
  assign cpol_o        = ctrl_reg[3];
  assign cpha_o        = ctrl_reg[4];
  assign lsb_first_o   = ctrl_reg[5];
  assign dma_en_o      = ctrl_reg[6];
  assign mode_en_o     = ctrl_reg[7];
  assign hold_en_o     = ctrl_reg[9];
  assign wp_en_o       = (HAS_WP!=0) ? ctrl_reg[10] : 1'b0;

  assign clk_div_o     = clk_div_reg[2:0];
  assign cs_auto_o     = cs_ctrl_reg[0];
  assign cs_level_o    = cs_ctrl_reg[2:1];
  assign cs_delay_o    = cs_ctrl_reg[4:3];

  assign xip_addr_bytes_o  = xip_cfg_reg[1:0];
  assign xip_data_lanes_o  = xip_cfg_reg[3:2];
  assign xip_dummy_cycles_o= xip_cfg_reg[7:4];
  assign xip_cont_read_o   = xip_cfg_reg[8];
  assign xip_mode_en_o     = xip_cfg_reg[9];
  assign xip_write_en_o    = xip_cfg_reg[10];
  assign xip_read_op_o     = xip_cmd_reg[7:0];
  assign xip_write_op_o    = xip_cmd_reg[15:8];
  assign xip_mode_bits_o   = xip_cmd_reg[23:16];

  assign cmd_lanes_o   = cmd_cfg_reg[1:0];
  assign addr_lanes_o  = cmd_cfg_reg[3:2];
  assign data_lanes_o  = cmd_cfg_reg[5:4];
  assign addr_bytes_o  = cmd_cfg_reg[7:6];
  assign mode_en_cfg_o = mode_en_o;
  assign dummy_cycles_o= cmd_cfg_reg[11:8];
  assign is_write_o    = cmd_cfg_reg[12];
  assign opcode_o      = cmd_op_reg[7:0];
  assign mode_bits_o   = cmd_op_reg[15:8];
  assign cmd_addr_o    = cmd_addr_reg;
  assign cmd_len_o     = cmd_len_reg;
  assign extra_dummy_o = cmd_dummy_reg[7:0];

  assign burst_size_o  = dma_cfg_reg[3:0];
  assign dma_dir_o     = dma_cfg_reg[4];
  assign incr_addr_o   = dma_cfg_reg[5];
  assign dma_addr_o    = dma_addr_reg;
  assign dma_len_o     = dma_len_reg;

  assign int_en_o      = int_en_reg[4:0];
  assign irq           = |(int_en_reg[4:0] & int_stat_reg[4:0]);

endmodule

tb/error_csr_tb.v
`timescale 1ns/1ps

// error_csr_tb - Unit test for CSR error/interrupt logic.
// Drives CSR directly to validate:
// - ERR_STAT W1C from timeout/overrun/underrun/axi_err inputs
// - INT_EN gating and irq assertion for cmd_done/dma_done/err

module error_csr_tb;
  reg clk; reg resetn;

  // APB
  reg        psel, penable, pwrite; reg [11:0] paddr; reg [31:0] pwdata; reg [3:0] pstrb;
  wire [31:0] prdata; wire pready; wire pslverr;

  // CSR sideband
  reg cmd_done_set_i, dma_done_set_i, err_set_i;
  reg [3:0] tx_level_i, rx_level_i; reg tx_empty_i, rx_full_i;
  reg busy_i, xip_active_i; reg cmd_done_i, dma_done_i;
  reg timeout_i, overrun_i, underrun_i, axi_err_i;
  wire irq;

  csr u_csr (
    .pclk(clk), .presetn(resetn),
    .psel(psel), .penable(penable), .pwrite(pwrite), .paddr(paddr), .pwdata(pwdata), .pstrb(pstrb),
    .prdata(prdata), .pready(pready), .pslverr(pslverr),
    .enable_o(), .xip_en_o(), .quad_en_o(), .cpol_o(), .cpha_o(), .lsb_first_o(),
    .cmd_start_o(), .dma_en_o(), .hold_en_o(), .wp_en_o(), .cmd_trigger_clr_i(1'b0),
    .clk_div_o(), .cs_auto_o(), .cs_level_o(), .cs_delay_o(),
    .xip_addr_bytes_o(), .xip_data_lanes_o(), .xip_dummy_cycles_o(), .xip_cont_read_o(), .xip_mode_en_o(), .xip_write_en_o(),
    .xip_read_op_o(), .xip_mode_bits_o(), .xip_write_op_o(),
    .cmd_lanes_o(), .addr_lanes_o(), .data_lanes_o(), .addr_bytes_o(), .mode_en_cfg_o(), .dummy_cycles_o(), .is_write_o(),
    .opcode_o(), .mode_bits_o(), .cmd_addr_o(), .cmd_len_o(), .extra_dummy_o(),
    .burst_size_o(), .dma_dir_o(), .incr_addr_o(), .dma_addr_o(), .dma_len_o(),
    .fifo_tx_data_o(), .fifo_tx_we_o(), .fifo_rx_data_i(32'h0), .fifo_rx_re_o(),
    .int_en_o(),
    .cmd_done_set_i(cmd_done_set_i), .dma_done_set_i(dma_done_set_i), .err_set_i(err_set_i), .fifo_tx_empty_set_i(1'b0), .fifo_rx_full_set_i(1'b0),
    .busy_i(busy_i), .xip_active_i(xip_active_i), .cmd_done_i(cmd_done_i), .dma_done_i(dma_done_i),
    .tx_level_i(tx_level_i), .rx_level_i(rx_level_i), .tx_empty_i(tx_empty_i), .rx_full_i(rx_full_i),
    .timeout_i(timeout_i), .overrun_i(overrun_i), .underrun_i(underrun_i), .axi_err_i(axi_err_i), .irq(irq)
  );

  // Clock
  initial clk=0; always #5 clk=~clk;

  // VCD + timeout
  initial begin $dumpfile("error_csr_tb.vcd"); $dumpvars(1, error_csr_tb); #5_000_000 $finish; end

  // APB helpers
  task apb_write(input [11:0] a, input [31:0] d);
  begin
    @(posedge clk); psel<=1; penable<=0; pwrite<=1; paddr<=a; pwdata<=d; pstrb<=4'hF;
    @(posedge clk); penable<=1; @(posedge clk);
    psel<=0; penable<=0; pwrite<=0; paddr<=0; pwdata<=0; pstrb<=0;
  end endtask
  task apb_read(input [11:0] a, output [31:0] d);
  begin
    @(posedge clk); psel<=1; penable<=0; pwrite<=0; paddr<=a; pstrb<=0;
    @(posedge clk); penable<=1; @(posedge clk); d=prdata;
    psel<=0; penable<=0; paddr<=0;
  end endtask

  localparam INT_EN=12'h00C, INT_STAT=12'h010, ERR_STAT=12'h050;

  integer pass, fail; reg [31:0] d;

  initial begin
    // init
    psel=0; penable=0; pwrite=0; paddr=0; pwdata=0; pstrb=0; resetn=0;
    cmd_done_set_i=0; dma_done_set_i=0; err_set_i=0; busy_i=0; xip_active_i=0; cmd_done_i=0; dma_done_i=0;
    tx_level_i=0; rx_level_i=0; tx_empty_i=1; rx_full_i=0; timeout_i=0; overrun_i=0; underrun_i=0; axi_err_i=0;
    pass=0; fail=0;
    repeat(5) @(posedge clk); resetn=1;

    // Enable all interrupts
    apb_write(INT_EN, 32'h0000_001F);

    // Trigger cmd_done and check IRQ + INT_STAT[0]
    cmd_done_set_i=1; @(posedge clk); cmd_done_set_i=0; @(posedge clk);
    apb_read(INT_STAT,d); if (d[0]!==1) begin $display("[FAIL] CMD_DONE"); fail=fail+1; end else pass=pass+1;
    if (!irq) begin $display("[FAIL] IRQ for CMD_DONE"); fail=fail+1; end else pass=pass+1;
    apb_write(INT_STAT, 32'h1);

    // Trigger dma_done and check IRQ + INT_STAT[1]
    dma_done_set_i=1; @(posedge clk); dma_done_set_i=0; @(posedge clk);
    apb_read(INT_STAT,d); if (d[1]!==1) begin $display("[FAIL] DMA_DONE"); fail=fail+1; end else pass=pass+1;
    if (!irq) begin $display("[FAIL] IRQ for DMA_DONE"); fail=fail+1; end else pass=pass+1;
    apb_write(INT_STAT, 32'h2);

    // Inject error status inputs and validate ERR_STAT W1C
    timeout_i=1; overrun_i=1; underrun_i=1; axi_err_i=1; @(posedge clk);
    timeout_i=0; overrun_i=0; underrun_i=0; axi_err_i=0; @(posedge clk);
    apb_read(ERR_STAT,d); if (d[3:0]!==4'hF) begin $display("[FAIL] ERR_STAT set"); fail=fail+1; end else pass=pass+1;
    apb_write(ERR_STAT, 32'hF); apb_read(ERR_STAT,d); if (d[3:0]!==4'h0) begin $display("[FAIL] ERR_STAT clear"); fail=fail+1; end else pass=pass+1;

    if (fail==0) $display("error_csr_tb: passed"); else $fatal(1, "error_csr_tb: FAIL (%0d)", fail);
    $finish;
  end
endmodule

error_csr_tb.vcd
$date
	Wed Sep 10 00:38:44 2025
$end
$version
	Icarus Verilog
$end
$timescale
	1ps
$end
$scope module error_csr_tb $end
$var wire 1 ! pready $end
$var wire 1 " pslverr $end
$var wire 32 # prdata [31:0] $end
$var wire 1 $ irq $end
$var reg 1 % axi_err_i $end
$var reg 1 & busy_i $end
$var reg 1 ' clk $end
$var reg 1 ( cmd_done_i $end
$var reg 1 ) cmd_done_set_i $end
$var reg 32 * d [31:0] $end
$var reg 1 + dma_done_i $end
$var reg 1 , dma_done_set_i $end
$var reg 1 - err_set_i $end
$var reg 1 . overrun_i $end
$var reg 12 / paddr [11:0] $end
$var reg 1 0 penable $end
$var reg 1 1 psel $end
$var reg 4 2 pstrb [3:0] $end
$var reg 32 3 pwdata [31:0] $end
$var reg 1 4 pwrite $end
$var reg 1 5 resetn $end
$var reg 1 6 rx_full_i $end
$var reg 4 7 rx_level_i [3:0] $end
$var reg 1 8 timeout_i $end
$var reg 1 9 tx_empty_i $end
$var reg 4 : tx_level_i [3:0] $end
$var reg 1 ; underrun_i $end
$var reg 1 < xip_active_i $end
$var integer 32 = fail [31:0] $end
$var integer 32 > pass [31:0] $end
$upscope $end
$enddefinitions $end
#0
$dumpvars
b0 >
b0 =
0<
0;
b0 :
19
08
b0 7
06
05
04
b0 3
b0 2
01
00
b0 /
0.
0-
0,
0+
bx *
0)
0(
0'
0&
0%
0$
b0 #
0"
1!
$end
#5000
1'
#10000
0'
#15000
1'
#20000
0'
#25000
1'
#30000
0'
#35000
1'
#40000
0'
#45000
15
1'
#50000
0'
#55000
b1111 2
b11111 3
b1100 /
14
11
1'
#60000
0'
#65000
10
1'
#70000
0'
#75000
1$
b0 2
b0 3
b0 /
04
00
01
1)
1'
#80000
0'
#85000
0)
1'
#90000
0'
#95000
1'
#100000
0'
#105000
b10000 /
11
1'
#110000
0'
#115000
b1 #
10
1'
#120000
0'
#125000
b0 #
b0 /
00
01
b10 >
b1 *
1'
#130000
0'
#135000
b1111 2
b1 3
b10000 /
14
11
1'
#140000
0'
#145000
10
1'
#150000
0'
#155000
b0 2
b0 3
b0 /
04
00
01
1,
1'
#160000
0'
#165000
0,
1'
#170000
0'
#175000
1'
#180000
0'
#185000
b10000 /
11
1'
#190000
0'
#195000
b10 #
10
1'
#200000
0'
#205000
b0 #
b0 /
00
01
b100 >
b10 *
1'
#210000
0'
#215000
b1111 2
b10 3
b10000 /
14
11
1'
#220000
0'
#225000
10
1'
#230000
0'
#235000
0$
b0 2
b0 3
b0 /
04
00
01
1%
1;
1.
18
1'
#240000
0'
#245000
0%
0;
0.
08
1'
#250000
0'
#255000
1'
#260000
0'
#265000
b1010000 /
11
1'
#270000
0'
#275000
b1111 #
10
1'
#280000
0'
#285000
b0 #
b0 /
00
01
b101 >
b1111 *
1'
#290000
0'
#295000
b1111 2
b1111 3
b1010000 /
14
11
1'
#300000
0'
#305000
10
1'
#310000
0'
#315000
b0 2
b0 3
b0 /
04
00
01
1'
#320000
0'
#325000
b1010000 /
11
1'
#330000
0'
#335000
10
1'
#340000
0'
#345000
b0 #
b0 /
00
01
b110 >
b0 *
1'
